modules/alu.v
// **************************************************
// ALU 
// **************************************************

module alu(
	input wire rst,
	input wire alu_immediate_enable,
	input wire [31:0] register_read_data_a,
	input wire [31:0] register_read_data_b,
	input wire [31:0] immediate_data,
	input wire [3:0] alu_operation,
	input wire [4:0] alu_shamt,
 	output reg [31:0] alu_out
);

wire [31:0] alu_input_1 = register_read_data_a; 
wire [31:0] alu_input_2 = alu_immediate_enable ? immediate_data : register_read_data_b;

always @(*) begin

	if (rst) begin
		alu_out <= 32'b0;
	end
	else begin
		case(alu_operation)
			4'b0001: alu_out <= (alu_input_1 - alu_input_2); // sub
			4'b0000: alu_out <= (alu_input_1 + alu_input_2); // add
			4'b0010: alu_out <= alu_input_1 << alu_shamt; // register-shift left
			4'b0011: alu_out <= ($signed(alu_input_1) < $signed(alu_input_2)); // set less than
			4'b0100: alu_out <= (alu_input_1 < alu_input_2); // set less than unsigned
			4'b0101: alu_out <= (alu_input_1 ^ alu_input_2); // xor
			4'b0110: alu_out <= ($signed(alu_input_1) >>> alu_shamt); // register-shift right arithmetic
			4'b0111: alu_out <= (alu_input_1 >> alu_shamt); // register-shift right logical
			4'b1000: alu_out <= (alu_input_1 | alu_input_2); // or
			4'b1001: alu_out <= (alu_input_1 & alu_input_2); // and
		endcase
	end
end

endmodule

modules/immediate_generator.v
// **************************************************
// Immediate Generator
// **************************************************

module immediate_generator(
	input wire [31:0] instruction_register,
	input wire [2:0] immediate_select,
	output wire [4:0] alu_shamt,
	output reg [31:0] immediate_data
);

// ---------- Parse Instruction Data ---------

wire Uimm = {    instruction_register[31],   instruction_register[30:12], {12{1'b0}}};                                                  // zero extend bits 11-0
wire Iimm = {{21{instruction_register[31]}}, instruction_register[30:20]};                                                              // sign extend bits 32-11
wire Simm = {{21{instruction_register[31]}}, instruction_register[30:25], instruction_register[11:7]};                                  // sign extend bits 31-11 
wire Bimm = {{20{instruction_register[31]}}, instruction_register[7], instruction_register[30:25], instruction_register[11:8], 1'b0};   // sign extend bits 31-12, bit 0 = 0 
wire Jimm = {{12{instruction_register[31]}}, instruction_register[19:12], instruction_register[20], instruction_register[30:21], 1'b0}; // sign extend bits 31-20, bit 0 = 0

// --------- Generate Immediate Data --------

always @(*) begin
	case(immediate_select)
		3'b000: immediate_data = Uimm; 
		3'b001: immediate_data = Iimm;
		3'b010: immediate_data = Simm;
		3'b011: immediate_data = Bimm;
		3'b100: immediate_data = Jimm;
		default: immediate_data = 8'h0; //Undefined Behavior
	endcase
end

// ------- ALU Shift Amount Calculator -------

assign alu_shamt = immediate_data[4:0];

endmodule

modules/register_file.v
// **************************************************
// 32 Wide (5 bit) 32 Bit Write-before-read Register File
// **************************************************

module register_file(
	input wire clk,
	input wire rst,
	input wire register_write_enable,
	input wire [4:0] register_write_address,
	input wire [4:0] register_read_address_a,
	input wire [4:0] register_read_address_b,
	input wire [31:0] register_write_data,
	output reg [31:0] register_read_data_a,
	output reg [31:0] register_read_data_b
);

// -------------- Register File --------------

reg [31:0] register_file [0:31];

// ---------------- W/R Logic ----------------

integer i;

always @(posedge clk) begin

	if (rst) begin
		for (i = 0; i < 32; i = i + 1)
			register_file[i] <= 32'b0;
	end 
	else begin

		register_read_data_a <= register_file[register_read_address_a];
    	register_read_data_b <= register_file[register_read_address_b];

		if (register_write_enable) begin
			register_file[register_write_address] <= register_write_data;

			if (register_write_address == register_read_address_a) begin
				register_read_data_a <= register_write_data; // Write-before-read explicit implementation
			end

			if (register_write_address == register_read_address_b) begin
				register_read_data_b <= register_write_data; // Write-before-read explicit implementation
			end  

		end

	end 
    
end

endmodule

modules/instruction_decoder.v
// **************************************************
// Core Control Unit
// **************************************************

module instruction_decoder(
	input wire [31:0] instruction_register,
	output wire register_write_enable,
	output wire alu_immediate_enable,
	output wire [2:0] immediate_select,
	output wire [4:0] register_write_address,
	output wire [4:0] register_read_address_a,
	output wire [4:0] register_read_address_b,
	output reg [3:0] alu_operation
);

// ------------- Wire Declaration ------------

wire [2:0] funct3 = instruction_register[14:12];
wire [6:0] funct7 = instruction_register[31:25];

// ---------- Parse Instruction Data ---------

wire alu_register_operation           = (instruction_register[6:2] == 5'b01100); // rd <- rs1 OP rs2
wire alu_immediate_operation          = (instruction_register[6:2] == 5'b00100); // rd <- rs1 OP Iimm
wire branch_operation                 = (instruction_register[6:2] == 5'b11000); // (rs1 OP rs2) ? PC <- PC + Bimm : nothing
wire jump_and_link_pc_operation       = (instruction_register[6:2] == 5'b01111); // rd <- PC + 4; PC <- PC + Jimm
wire jump_and_link_register_operation = (instruction_register[6:2] == 5'b11001); // rd <- PC + 4; PC <- rs1 + Iimm
wire add_upper_immediate_pc_operation = (instruction_register[6:2] == 5'b00101); // rd <- PC + Uimm 
wire load_upper_immediate_operation   = (instruction_register[6:2] == 5'b01101); // rd <- Uimm
wire load_operation                   = (instruction_register[6:2] == 5'b00000); // rd <- memory[rs1 + Iimm]
wire store_operation                  = (instruction_register[6:2] == 5'b01000); // memory[rs1 + Simm] <- rs2
wire system_operation                 = (instruction_register[6:2] == 5'b11100); // reserved

// ---------- ALU Operation Control ----------

always @(*) begin
	case(funct3) 
		3'b000: alu_operation = (funct7[5] & instruction_register[5]) ? (4'b0001) : // sub
		(4'b0000); // add
		3'b001: alu_operation = 4'b0010; // register-shift left
		3'b010: alu_operation = 4'b0011; // set less than
		3'b011: alu_operation = 4'b0100; // set less than unsigned
		3'b100: alu_operation = 4'b0101; // xor
		3'b101: alu_operation = funct7[5] ? (4'b0110) : // register-shift right arithmetic
		(4'b0111); // register-shift right logical
		3'b110: alu_operation = (4'b1000); // or
		3'b111: alu_operation = (4'b1001); // and
	endcase
end

// ------ ALU Immediate Select Control ------

assign alu_immediate_enable = alu_immediate_operation ? 1'b1 : 1'b0;

// --------- Register Write Control ---------

assign register_write_address = instruction_register[11:7];
assign register_read_address_a = instruction_register[19:15];
assign register_read_address_b = instruction_register[24:20];

assign register_write_enable = alu_register_operation ? 1'b1 : 
	alu_immediate_operation ? 1'b1 :
	jump_and_link_pc_operation ? 1'b1 :
	add_upper_immediate_pc_operation ? 1'b1 :
	load_operation ? 1'b1 :
	1'b0;

// ------- Immediate Generator Control -------

assign immediate_select = alu_register_operation ? 3'b111 : // Unused 
	alu_immediate_operation ? 3'b001 : // Iimm
	branch_operation ? 3'b011 : // Bimm
	jump_and_link_register_operation ? 3'b001 : // Iimm
	add_upper_immediate_pc_operation ? 3'b000 : // Uimm
	load_upper_immediate_operation ? 3'b000 : // Uimm
	load_operation ? 3'b001 : // Iimm
	store_operation ? 3'b010 : // Simm
	system_operation ? 3'b111 : // Unused
	3'b111; // Base Case

endmodule

modules/instruction_register.v
module instruction_register (
    input wire clk,
    input wire rst,
    input wire [31:0] memory_read_data_a,
    output reg [31:0] instruction_register
);

always @(posedge clk) begin

    if (rst) begin
        instruction_register <= 32'b0;
    end 
    else begin
        instruction_register <= memory_read_data_a;
    end
    
end

endmodule

modules/memory.v
// **************************************************
// Full Dual-Port Memory (12 bit block)
// **************************************************

module memory (
	input clk_a,
	input memory_write_enable_a,
	input [31:0] memory_access_address_a,
	input [31:0] memory_write_data_a,
	output reg [31:0] memory_read_data_a,
	
	input clk_b,
	input memory_write_enable_b,
	input [31:0] memory_access_address_b,
	input [31:0] memory_write_data_b,
	output reg [31:0] memory_read_data_b
);

// -------------- Memory Block --------------

reg [31:0] memory[0:4095];

initial $readmemh("mem.hex", memory);

// ----------------- Port A -----------------

always @(posedge clk_a) begin
    memory_read_data_a <= memory[memory_access_address_a];

    if (memory_write_enable_a) begin
        memory_read_data_a <= memory_write_data_a; // Write-before-read explicit implementation
        memory[memory_access_address_a] <= memory_write_data_a;
    end

end

// ----------------- Port B -----------------

always @(posedge clk_b) begin
    memory_read_data_b <= memory[memory_access_address_b];

    if (memory_write_enable_b) begin
        memory_read_data_b <= memory_write_data_b; // Write-before-read explicit implementation
        memory[memory_access_address_b] <= memory_write_data_b;
    end
    
end

endmodule

modules/program_counter.v
// **************************************************
// Program Counter
// **************************************************

module program_counter(
	input wire clk,
	input wire rst,
	output reg[31:0] program_counter
);

always @(posedge clk) begin

	if (rst) begin
			program_counter <= 32'b0;
	end
	else begin 
		program_counter <= program_counter + 1;
	end
	
end

endmodule

modules/waverv.v
// **************************************************
// Root/Instantiator Module
// **************************************************

module waverv (
	input clk,
	input rst
);

// ------ Wire Declaration By Originator -----

// Program Counter
wire [31:0] program_counter;

// Memory
wire [31:0] memory_read_data_a;
wire [31:0] memory_read_data_b;

// Instruction Register
wire [31:0] instruction_register;

// Instruction Decoder
wire register_write_enable;
wire alu_immediate_enable;
wire [2:0] immediate_select;
wire [4:0] register_write_address;
wire [4:0] register_read_address_a;
wire [4:0] register_read_address_b;
wire [3:0] alu_operation;

// Register File
wire [31:0] register_read_data_a;
wire [31:0] register_read_data_b;

// Immediate Generator
wire [4:0] alu_shamt;
wire [31:0] immediate_data;

// ALU
wire [31:0] alu_out;

// ----------- Module Instantiation ----------

program_counter program_counter_inst(
	.clk(clk),
	.rst(rst),
	.program_counter(program_counter)
);

memory memory_inst (
	.clk_a(clk),
	.memory_write_enable_a(1'b0),
	.memory_access_address_a(program_counter),
	.memory_write_data_a(32'b0),
	.memory_read_data_a(memory_read_data_a)
);

instruction_register instruction_register_inst (
	.clk(clk),
	.rst(rst),
	.memory_read_data_a(memory_read_data_a),
	.instruction_register(instruction_register)
);

instruction_decoder instruction_decoder_inst (
	.instruction_register(instruction_register),
	.register_write_enable(register_write_enable),
	.alu_immediate_enable(alu_immediate_enable),
	.immediate_select(immediate_select),
	.register_write_address(register_write_address),
	.register_read_address_a(register_read_address_a),
	.register_read_address_b(register_read_address_b),
	.alu_operation(alu_operation)
);

register_file register_file_inst (
	.clk(clk),
	.register_write_enable(register_write_enable),
	.register_write_address(register_write_address),
	.register_read_address_a(register_read_address_a),
	.register_read_address_b(register_read_address_b),
	.register_write_data(alu_out),
	.register_read_data_a(register_read_data_a),
	.register_read_data_b(register_read_data_b)
);

immediate_generator immediate_generator_inst (
	.instruction_register(instruction_register),
	.immediate_select(immediate_select),
	.alu_shamt(alu_shamt),
	.immediate_data(immediate_data)
);

alu alu_inst (
	.rst(rst),
	.alu_immediate_enable(alu_immediate_enable),
	.register_read_data_a(register_read_data_a),
	.register_read_data_b(register_read_data_b),
	.immediate_data(immediate_data),
	.alu_operation(alu_operation),
	.alu_shamt(alu_shamt),
	.alu_out(alu_out)
);

endmodule

modules/test_bench.v
`timescale 1ps/1ps

module test_bench;

reg clk;
reg rst;

waverv waverv_inst (
    .clk(clk),
    .rst(rst)
);

initial begin 

    $dumpfile("counter.vcd");
    $dumpvars(0, test_bench);

    rst = 1;
    #5;
    rst = 0;

    #1000;
    $finish;
end

initial clk = 0;
always #1 clk = ~clk;

endmodule

test_data/counter.vcd
$date
	Thu Jan  8 20:32:00 2026
$end
$version
	Icarus Verilog
$end
$timescale
	1ps
$end
$scope module test_bench $end
$var reg 1 ! clk $end
$var reg 1 " rst $end
$scope module waverv_inst $end
$var wire 1 ! clk $end
$var wire 1 " rst $end
$var wire 1 # register_write_enable $end
$var wire 5 $ register_write_address [4:0] $end
$var wire 32 % register_read_data_b [31:0] $end
$var wire 32 & register_read_data_a [31:0] $end
$var wire 5 ' register_read_address_b [4:0] $end
$var wire 5 ( register_read_address_a [4:0] $end
$var wire 32 ) program_counter [31:0] $end
$var wire 32 * memory_read_data_a [31:0] $end
$var wire 32 + instruction_register [31:0] $end
$var wire 3 , immediate_select [2:0] $end
$var wire 32 - immediate_data [31:0] $end
$var wire 5 . alu_shamt [4:0] $end
$var wire 32 / alu_out [31:0] $end
$var wire 4 0 alu_operation [3:0] $end
$var wire 1 1 alu_immediate_enable $end
$scope module alu_inst $end
$var wire 32 2 alu_input_1 [31:0] $end
$var wire 1 " rst $end
$var wire 32 3 register_read_data_b [31:0] $end
$var wire 32 4 register_read_data_a [31:0] $end
$var wire 32 5 immediate_data [31:0] $end
$var wire 5 6 alu_shamt [4:0] $end
$var wire 4 7 alu_operation [3:0] $end
$var wire 32 8 alu_input_2 [31:0] $end
$var wire 1 1 alu_immediate_enable $end
$var reg 32 9 alu_out [31:0] $end
$upscope $end
$scope module immediate_generator_inst $end
$var wire 32 : instruction_register [31:0] $end
$var wire 3 ; immediate_select [2:0] $end
$var wire 5 < alu_shamt [4:0] $end
$var wire 1 = Uimm $end
$var wire 1 > Simm $end
$var wire 1 ? Jimm $end
$var wire 1 @ Iimm $end
$var wire 1 A Bimm $end
$var reg 32 B immediate_data [31:0] $end
$upscope $end
$scope module instruction_decoder_inst $end
$var wire 1 C system_operation $end
$var wire 1 D store_operation $end
$var wire 1 # register_write_enable $end
$var wire 5 E register_write_address [4:0] $end
$var wire 5 F register_read_address_b [4:0] $end
$var wire 5 G register_read_address_a [4:0] $end
$var wire 1 H load_upper_immediate_operation $end
$var wire 1 I load_operation $end
$var wire 1 J jump_and_link_register_operation $end
$var wire 1 K jump_and_link_pc_operation $end
$var wire 32 L instruction_register [31:0] $end
$var wire 3 M immediate_select [2:0] $end
$var wire 7 N funct7 [6:0] $end
$var wire 3 O funct3 [2:0] $end
$var wire 1 P branch_operation $end
$var wire 1 Q alu_register_operation $end
$var wire 1 R alu_immediate_operation $end
$var wire 1 1 alu_immediate_enable $end
$var wire 1 S add_upper_immediate_pc_operation $end
$var reg 4 T alu_operation [3:0] $end
$upscope $end
$scope module instruction_register_inst $end
$var wire 1 ! clk $end
$var wire 1 " rst $end
$var wire 32 U memory_read_data_a [31:0] $end
$var reg 32 V instruction_register [31:0] $end
$upscope $end
$scope module memory_inst $end
$var wire 1 ! clk_a $end
$var wire 1 W clk_b $end
$var wire 32 X memory_access_address_b [31:0] $end
$var wire 32 Y memory_write_data_a [31:0] $end
$var wire 32 Z memory_write_data_b [31:0] $end
$var wire 1 [ memory_write_enable_a $end
$var wire 1 \ memory_write_enable_b $end
$var wire 32 ] memory_access_address_a [31:0] $end
$var reg 32 ^ memory_read_data_a [31:0] $end
$var reg 32 _ memory_read_data_b [31:0] $end
$upscope $end
$scope module program_counter_inst $end
$var wire 1 ! clk $end
$var wire 1 " rst $end
$var reg 32 ` program_counter [31:0] $end
$upscope $end
$scope module register_file_inst $end
$var wire 1 ! clk $end
$var wire 5 a register_read_address_a [4:0] $end
$var wire 5 b register_read_address_b [4:0] $end
$var wire 5 c register_write_address [4:0] $end
$var wire 32 d register_write_data [31:0] $end
$var wire 1 # register_write_enable $end
$var wire 1 e rst $end
$var reg 32 f register_read_data_a [31:0] $end
$var reg 32 g register_read_data_b [31:0] $end
$var integer 32 h i [31:0] $end
$upscope $end
$upscope $end
$upscope $end
$enddefinitions $end
$comment Show the parameter values. $end
$dumpall
$end
#0
$dumpvars
bx h
bx g
bx f
ze
b0 d
bx c
bx b
bx a
bx `
bx _
bx ^
bx ]
z\
0[
bz Z
b0 Y
bz X
zW
bx V
bx U
bx T
xS
xR
xQ
xP
bx O
bx N
bx M
bx L
xK
xJ
xI
xH
bx G
bx F
bx E
xD
xC
b0 B
0A
x@
0?
x>
0=
b0 <
bx ;
bx :
b0 9
bx 8
bx 7
b0 6
b0 5
bx 4
bx 3
bx 2
x1
bx 0
b0 /
b0 .
b0 -
bx ,
bx +
bx *
bx )
bx (
bx '
bx &
bx %
bx $
x#
1"
0!
$end
#1
b1 ,
b1 ;
b1 M
1#
01
b0 0
b0 7
b0 T
0>
0@
b0 '
b0 F
b0 b
b0 (
b0 G
b0 a
b0 $
b0 E
b0 c
0C
0D
1I
0H
0S
0J
0K
0P
0R
0Q
b0 N
b0 O
b0 )
b0 ]
b0 `
b0 +
b0 :
b0 L
b0 V
1!
#2
0!
#3
b0 8
b0 %
b0 3
b0 g
b0 2
b0 &
b0 4
b0 f
b0 *
b0 U
b0 ^
1!
#4
0!
#5
b1 )
b1 ]
b1 `
1!
0"
#6
0!
#7
b10 )
b10 ]
b10 `
1!
#8
0!
#9
b11 )
b11 ]
b11 `
1!
#10
0!
#11
b100001000000010010011 *
b100001000000010010011 U
b100001000000010010011 ^
b100 )
b100 ]
b100 `
1!
#12
0!
#13
b1 /
b1 9
b1 d
b1 .
b1 6
b1 <
b1 8
b1 -
b1 5
b1 B
11
1>
1@
b1 '
b1 F
b1 b
b1 (
b1 G
b1 a
b1 $
b1 E
b1 c
0I
1R
b101 )
b101 ]
b101 `
b100001000000010110011 *
b100001000000010110011 U
b100001000000010110011 ^
b100001000000010010011 +
b100001000000010010011 :
b100001000000010010011 L
b100001000000010010011 V
1!
#14
0!
#15
b10 /
b10 9
b10 d
b0 .
b0 6
b0 <
b0 -
b0 5
b0 B
01
b111 ,
b111 ;
b111 M
0R
1Q
b1 %
b1 3
b1 g
b1 2
b1 &
b1 4
b1 f
b100001000000010110011 +
b100001000000010110011 :
b100001000000010110011 L
b100001000000010110011 V
b110 )
b110 ]
b110 `
1!
#16
0!
#17
b100 /
b100 9
b100 d
b10 8
b111 )
b111 ]
b111 `
b10 %
b10 3
b10 g
b10 2
b10 &
b10 4
b10 f
1!
#18
0!
#19
b1000 /
b1000 9
b1000 d
b100 8
b100 %
b100 3
b100 g
b100 2
b100 &
b100 4
b100 f
b1000 )
b1000 ]
b1000 `
1!
#20
0!
#21
b10000 /
b10000 9
b10000 d
b1000 8
b1001 )
b1001 ]
b1001 `
b1000 %
b1000 3
b1000 g
b1000 2
b1000 &
b1000 4
b1000 f
1!
#22
0!
#23
b100000 /
b100000 9
b100000 d
b10000 8
b10000 %
b10000 3
b10000 g
b10000 2
b10000 &
b10000 4
b10000 f
b1010 )
b1010 ]
b1010 `
1!
#24
0!
#25
b1000000 /
b1000000 9
b1000000 d
b100000 8
b1011 )
b1011 ]
b1011 `
b100000 %
b100000 3
b100000 g
b100000 2
b100000 &
b100000 4
b100000 f
1!
#26
0!
#27
b10000000 /
b10000000 9
b10000000 d
b1000000 8
b1000000 %
b1000000 3
b1000000 g
b1000000 2
b1000000 &
b1000000 4
b1000000 f
b1100 )
b1100 ]
b1100 `
1!
#28
0!
#29
b100000000 /
b100000000 9
b100000000 d
b10000000 8
b1101 )
b1101 ]
b1101 `
b10000000 %
b10000000 3
b10000000 g
b10000000 2
b10000000 &
b10000000 4
b10000000 f
1!
#30
0!
#31
b1000000000 /
b1000000000 9
b1000000000 d
b100000000 8
b100000000 %
b100000000 3
b100000000 g
b100000000 2
b100000000 &
b100000000 4
b100000000 f
b1110 )
b1110 ]
b1110 `
1!
#32
0!
#33
b10000000000 /
b10000000000 9
b10000000000 d
b1000000000 8
b1111 )
b1111 ]
b1111 `
b1000000000 %
b1000000000 3
b1000000000 g
b1000000000 2
b1000000000 &
b1000000000 4
b1000000000 f
1!
#34
0!
#35
b100000000000 /
b100000000000 9
b100000000000 d
b10000000000 8
b10000000000 %
b10000000000 3
b10000000000 g
b10000000000 2
b10000000000 &
b10000000000 4
b10000000000 f
b10000 )
b10000 ]
b10000 `
1!
#36
0!
#37
b1000000000000 /
b1000000000000 9
b1000000000000 d
b100000000000 8
b10001 )
b10001 ]
b10001 `
b100000000000 %
b100000000000 3
b100000000000 g
b100000000000 2
b100000000000 &
b100000000000 4
b100000000000 f
1!
#38
0!
#39
b10000000000000 /
b10000000000000 9
b10000000000000 d
b1000000000000 8
b1000000000000 %
b1000000000000 3
b1000000000000 g
b1000000000000 2
b1000000000000 &
b1000000000000 4
b1000000000000 f
b10010 )
b10010 ]
b10010 `
1!
#40
0!
#41
b100000000000000 /
b100000000000000 9
b100000000000000 d
b10000000000000 8
b10011 )
b10011 ]
b10011 `
b10000000000000 %
b10000000000000 3
b10000000000000 g
b10000000000000 2
b10000000000000 &
b10000000000000 4
b10000000000000 f
1!
#42
0!
#43
b1000000000000000 /
b1000000000000000 9
b1000000000000000 d
b100000000000000 8
b100000000000000 %
b100000000000000 3
b100000000000000 g
b100000000000000 2
b100000000000000 &
b100000000000000 4
b100000000000000 f
b10100 )
b10100 ]
b10100 `
1!
#44
0!
#45
b10000000000000000 /
b10000000000000000 9
b10000000000000000 d
b1000000000000000 8
b10101 )
b10101 ]
b10101 `
b1000000000000000 %
b1000000000000000 3
b1000000000000000 g
b1000000000000000 2
b1000000000000000 &
b1000000000000000 4
b1000000000000000 f
1!
#46
0!
#47
b100000000000000000 /
b100000000000000000 9
b100000000000000000 d
b10000000000000000 8
b10000000000000000 %
b10000000000000000 3
b10000000000000000 g
b10000000000000000 2
b10000000000000000 &
b10000000000000000 4
b10000000000000000 f
b10110 )
b10110 ]
b10110 `
1!
#48
0!
#49
b1000000000000000000 /
b1000000000000000000 9
b1000000000000000000 d
b100000000000000000 8
b10111 )
b10111 ]
b10111 `
b100000000000000000 %
b100000000000000000 3
b100000000000000000 g
b100000000000000000 2
b100000000000000000 &
b100000000000000000 4
b100000000000000000 f
1!
#50
0!
#51
b10000000000000000000 /
b10000000000000000000 9
b10000000000000000000 d
b1000000000000000000 8
b1000000000000000000 %
b1000000000000000000 3
b1000000000000000000 g
b1000000000000000000 2
b1000000000000000000 &
b1000000000000000000 4
b1000000000000000000 f
b11000 )
b11000 ]
b11000 `
1!
#52
0!
#53
b100000000000000000000 /
b100000000000000000000 9
b100000000000000000000 d
b10000000000000000000 8
b11001 )
b11001 ]
b11001 `
b10000000000000000000 %
b10000000000000000000 3
b10000000000000000000 g
b10000000000000000000 2
b10000000000000000000 &
b10000000000000000000 4
b10000000000000000000 f
1!
#54
0!
#55
b1000000000000000000000 /
b1000000000000000000000 9
b1000000000000000000000 d
b100000000000000000000 8
b100000000000000000000 %
b100000000000000000000 3
b100000000000000000000 g
b100000000000000000000 2
b100000000000000000000 &
b100000000000000000000 4
b100000000000000000000 f
b11010 )
b11010 ]
b11010 `
1!
#56
0!
#57
b10000000000000000000000 /
b10000000000000000000000 9
b10000000000000000000000 d
b1000000000000000000000 8
b11011 )
b11011 ]
b11011 `
b1000000000000000000000 %
b1000000000000000000000 3
b1000000000000000000000 g
b1000000000000000000000 2
b1000000000000000000000 &
b1000000000000000000000 4
b1000000000000000000000 f
1!
#58
0!
#59
b100000000000000000000000 /
b100000000000000000000000 9
b100000000000000000000000 d
b10000000000000000000000 8
b10000000000000000000000 %
b10000000000000000000000 3
b10000000000000000000000 g
b10000000000000000000000 2
b10000000000000000000000 &
b10000000000000000000000 4
b10000000000000000000000 f
b11100 )
b11100 ]
b11100 `
1!
#60
0!
#61
b1000000000000000000000000 /
b1000000000000000000000000 9
b1000000000000000000000000 d
b100000000000000000000000 8
b11101 )
b11101 ]
b11101 `
b100000000000000000000000 %
b100000000000000000000000 3
b100000000000000000000000 g
b100000000000000000000000 2
b100000000000000000000000 &
b100000000000000000000000 4
b100000000000000000000000 f
1!
#62
0!
#63
b10000000000000000000000000 /
b10000000000000000000000000 9
b10000000000000000000000000 d
b1000000000000000000000000 8
b1000000000000000000000000 %
b1000000000000000000000000 3
b1000000000000000000000000 g
b1000000000000000000000000 2
b1000000000000000000000000 &
b1000000000000000000000000 4
b1000000000000000000000000 f
b11110 )
b11110 ]
b11110 `
1!
#64
0!
#65
b100000000000000000000000000 /
b100000000000000000000000000 9
b100000000000000000000000000 d
b10000000000000000000000000 8
b11111 )
b11111 ]
b11111 `
b10000000000000000000000000 %
b10000000000000000000000000 3
b10000000000000000000000000 g
b10000000000000000000000000 2
b10000000000000000000000000 &
b10000000000000000000000000 4
b10000000000000000000000000 f
1!
#66
0!
#67
b1000000000000000000000000000 /
b1000000000000000000000000000 9
b1000000000000000000000000000 d
b100000000000000000000000000 8
b100000000000000000000000000 %
b100000000000000000000000000 3
b100000000000000000000000000 g
b100000000000000000000000000 2
b100000000000000000000000000 &
b100000000000000000000000000 4
b100000000000000000000000000 f
b100000 )
b100000 ]
b100000 `
1!
#68
0!
#69
b10000000000000000000000000000 /
b10000000000000000000000000000 9
b10000000000000000000000000000 d
b1000000000000000000000000000 8
b100001 )
b100001 ]
b100001 `
b1000000000000000000000000000 %
b1000000000000000000000000000 3
b1000000000000000000000000000 g
b1000000000000000000000000000 2
b1000000000000000000000000000 &
b1000000000000000000000000000 4
b1000000000000000000000000000 f
1!
#70
0!
#71
b100000000000000000000000000000 /
b100000000000000000000000000000 9
b100000000000000000000000000000 d
b10000000000000000000000000000 8
b10000000000000000000000000000 %
b10000000000000000000000000000 3
b10000000000000000000000000000 g
b10000000000000000000000000000 2
b10000000000000000000000000000 &
b10000000000000000000000000000 4
b10000000000000000000000000000 f
b100010 )
b100010 ]
b100010 `
1!
#72
0!
#73
b1000000000000000000000000000000 /
b1000000000000000000000000000000 9
b1000000000000000000000000000000 d
b100000000000000000000000000000 8
b100011 )
b100011 ]
b100011 `
b100000000000000000000000000000 %
b100000000000000000000000000000 3
b100000000000000000000000000000 g
b100000000000000000000000000000 2
b100000000000000000000000000000 &
b100000000000000000000000000000 4
b100000000000000000000000000000 f
1!
#74
0!
#75
b10000000000000000000000000000000 /
b10000000000000000000000000000000 9
b10000000000000000000000000000000 d
b1000000000000000000000000000000 8
b1000000000000000000000000000000 %
b1000000000000000000000000000000 3
b1000000000000000000000000000000 g
b1000000000000000000000000000000 2
b1000000000000000000000000000000 &
b1000000000000000000000000000000 4
b1000000000000000000000000000000 f
b100100 )
b100100 ]
b100100 `
1!
#76
0!
#77
b0 /
b0 9
b0 d
b10000000000000000000000000000000 8
b100101 )
b100101 ]
b100101 `
b10000000000000000000000000000000 %
b10000000000000000000000000000000 3
b10000000000000000000000000000000 g
b10000000000000000000000000000000 2
b10000000000000000000000000000000 &
b10000000000000000000000000000000 4
b10000000000000000000000000000000 f
1!
#78
0!
#79
b0 /
b0 9
b0 d
b0 8
b0 %
b0 3
b0 g
b0 2
b0 &
b0 4
b0 f
b100110 )
b100110 ]
b100110 `
1!
#80
0!
#81
b100111 )
b100111 ]
b100111 `
1!
#82
0!
#83
b101000 )
b101000 ]
b101000 `
1!
#84
0!
#85
b101001 )
b101001 ]
b101001 `
1!
#86
0!
#87
b101010 )
b101010 ]
b101010 `
1!
#88
0!
#89
b101011 )
b101011 ]
b101011 `
1!
#90
0!
#91
b101100 )
b101100 ]
b101100 `
1!
#92
0!
#93
b101101 )
b101101 ]
b101101 `
1!
#94
0!
#95
b101110 )
b101110 ]
b101110 `
1!
#96
0!
#97
b101111 )
b101111 ]
b101111 `
1!
#98
0!
#99
b110000 )
b110000 ]
b110000 `
1!
#100
0!
#101
b110001 )
b110001 ]
b110001 `
1!
#102
0!
#103
b110010 )
b110010 ]
b110010 `
1!
#104
0!
#105
b110011 )
b110011 ]
b110011 `
1!
#106
0!
#107
b110100 )
b110100 ]
b110100 `
1!
#108
0!
#109
b110101 )
b110101 ]
b110101 `
1!
#110
0!
#111
b110110 )
b110110 ]
b110110 `
1!
#112
0!
#113
b110111 )
b110111 ]
b110111 `
1!
#114
0!
#115
b111000 )
b111000 ]
b111000 `
1!
#116
0!
#117
b111001 )
b111001 ]
b111001 `
1!
#118
0!
#119
b111010 )
b111010 ]
b111010 `
1!
#120
0!
#121
b111011 )
b111011 ]
b111011 `
1!
#122
0!
#123
b111100 )
b111100 ]
b111100 `
1!
#124
0!
#125
b111101 )
b111101 ]
b111101 `
1!
#126
0!
#127
b111110 )
b111110 ]
b111110 `
1!
#128
0!
#129
b111111 )
b111111 ]
b111111 `
1!
#130
0!
#131
b1000000 )
b1000000 ]
b1000000 `
1!
#132
0!
#133
b1000001 )
b1000001 ]
b1000001 `
1!
#134
0!
#135
b1000010 )
b1000010 ]
b1000010 `
1!
#136
0!
#137
b1000011 )
b1000011 ]
b1000011 `
1!
#138
0!
#139
b1000100 )
b1000100 ]
b1000100 `
1!
#140
0!
#141
b1000101 )
b1000101 ]
b1000101 `
1!
#142
0!
#143
b1000110 )
b1000110 ]
b1000110 `
1!
#144
0!
#145
b1000111 )
b1000111 ]
b1000111 `
1!
#146
0!
#147
b1001000 )
b1001000 ]
b1001000 `
1!
#148
0!
#149
b1001001 )
b1001001 ]
b1001001 `
1!
#150
0!
#151
b1001010 )
b1001010 ]
b1001010 `
1!
#152
0!
#153
b1001011 )
b1001011 ]
b1001011 `
1!
#154
0!
#155
b1001100 )
b1001100 ]
b1001100 `
1!
#156
0!
#157
b1001101 )
b1001101 ]
b1001101 `
1!
#158
0!
#159
b1001110 )
b1001110 ]
b1001110 `
1!
#160
0!
#161
b1001111 )
b1001111 ]
b1001111 `
1!
#162
0!
#163
b1010000 )
b1010000 ]
b1010000 `
1!
#164
0!
#165
b1010001 )
b1010001 ]
b1010001 `
1!
#166
0!
#167
b1010010 )
b1010010 ]
b1010010 `
1!
#168
0!
#169
b1010011 )
b1010011 ]
b1010011 `
1!
#170
0!
#171
b1010100 )
b1010100 ]
b1010100 `
1!
#172
0!
#173
b1010101 )
b1010101 ]
b1010101 `
1!
#174
0!
#175
b1010110 )
b1010110 ]
b1010110 `
1!
#176
0!
#177
b1010111 )
b1010111 ]
b1010111 `
1!
#178
0!
#179
b1011000 )
b1011000 ]
b1011000 `
1!
#180
0!
#181
b1011001 )
b1011001 ]
b1011001 `
1!
#182
0!
#183
b1011010 )
b1011010 ]
b1011010 `
1!
#184
0!
#185
b1011011 )
b1011011 ]
b1011011 `
1!
#186
0!
#187
b1011100 )
b1011100 ]
b1011100 `
1!
#188
0!
#189
b1011101 )
b1011101 ]
b1011101 `
1!
#190
0!
#191
b1011110 )
b1011110 ]
b1011110 `
1!
#192
0!
#193
b1011111 )
b1011111 ]
b1011111 `
1!
#194
0!
#195
b1100000 )
b1100000 ]
b1100000 `
1!
#196
0!
#197
b1100001 )
b1100001 ]
b1100001 `
1!
#198
0!
#199
b1100010 )
b1100010 ]
b1100010 `
1!
#200
0!
#201
b1100011 )
b1100011 ]
b1100011 `
1!
#202
0!
#203
b1100100 )
b1100100 ]
b1100100 `
1!
#204
0!
