modules/alu.v
// **************************************************
// ALU 
// **************************************************

module alu(
	input wire rst,
	input wire alu_immediate_enable,
	input wire [31:0] register_read_data_a,
	input wire [31:0] register_read_data_b,
	input wire [31:0] immediate_data,
	input wire [3:0] alu_operation,
	input wire [4:0] alu_shamt,
 	output reg [31:0] alu_out
);

wire [31:0] alu_input_1 = register_read_data_a; 
wire [31:0] alu_input_2 = alu_immediate_enable ? immediate_data : register_read_data_b;

always @(*) begin
	if (~rst) begin
		alu_out <= 32'b0;
	end else begin
		case(alu_operation)
			4'b0001: alu_out <= (alu_input_1 - alu_input_2); // sub
			4'b0000: alu_out <= (alu_input_1 + alu_input_2); // add
			4'b0010: alu_out <= alu_input_1 << alu_shamt; // register-shift left
			4'b0011: alu_out <= ($signed(alu_input_1) < $signed(alu_input_2)); // set less than
			4'b0100: alu_out <= (alu_input_1 < alu_input_2); // set less than unsigned
			4'b0101: alu_out <= (alu_input_1 ^ alu_input_2); // xor
			4'b0110: alu_out <= ($signed(alu_input_1) >>> alu_shamt); // register-shift right arithmetic
			4'b0111: alu_out <= (alu_input_1 >> alu_shamt); // register-shift right logical
			4'b1000: alu_out <= (alu_input_1 | alu_input_2); // or
			4'b1001: alu_out <= (alu_input_1 & alu_input_2); // and
		endcase
	end
end

endmodule

modules/immediate_generator.v
// **************************************************
// Immediate Generator
// **************************************************

module immediate_generator(
	input wire [31:0] instruction_register,
	input wire [2:0] immediate_select,
	output wire [4:0] alu_shamt,
	output reg [31:0] immediate_data
);

// ---------- Parse Instruction Data ---------

wire Uimm = {    instruction_register[31],   instruction_register[30:12], {12{1'b0}}};                                                  // zero extend bits 11-0
wire Iimm = {{21{instruction_register[31]}}, instruction_register[30:20]};                                                              // sign extend bits 32-11
wire Simm = {{21{instruction_register[31]}}, instruction_register[30:25], instruction_register[11:7]};                                  // sign extend bits 31-11 
wire Bimm = {{20{instruction_register[31]}}, instruction_register[7], instruction_register[30:25], instruction_register[11:8], 1'b0};   // sign extend bits 31-12, bit 0 = 0 
wire Jimm = {{12{instruction_register[31]}}, instruction_register[19:12], instruction_register[20], instruction_register[30:21], 1'b0}; // sign extend bits 31-20, bit 0 = 0

// --------- Generate Immediate Data --------

always @(*) begin
	case(immediate_select)
		3'b000: immediate_data = Uimm; 
		3'b001: immediate_data = Iimm;
		3'b010: immediate_data = Simm;
		3'b011: immediate_data = Bimm;
		3'b100: immediate_data = Jimm;
		default: immediate_data = 8'h0; //Undefined Behavior
	endcase
end

// ------- ALU Shift Amount Calculator -------

assign alu_shamt = immediate_data[4:0];

endmodule

modules/register_file.v
// **************************************************
// 32 Wide (5 bit) 32 Bit Write-before-read Register File
// **************************************************

module register_file(
	input wire clk,
	input wire rst,
	input wire register_write_enable,
	input wire data_memory_write_back_enable,
	input wire [4:0] register_write_address,
	input wire [4:0] register_read_address_a,
	input wire [4:0] register_read_address_b,
	input wire [31:0] alu_out,
	input wire [31:0] data_memory_read_data,
	output wire [31:0] register_read_data_a,
	output wire [31:0] register_read_data_b
);

// -------- Memory Write Back Control --------

wire [31:0] register_write_data = data_memory_write_back_enable ? data_memory_read_data : alu_out;

// -------------- Register File --------------

reg [31:0] register_file [0:31];

// ---------------- W/R Logic ----------------

assign register_read_data_a = register_file[register_read_address_a];
assign register_read_data_b = register_file[register_read_address_b];

always @(posedge clk) begin

	if (~rst) begin
		for (integer i = 0; i < 32; i = i + 1)
			register_file[i] <= 32'b0;
	end else begin

		if (register_write_enable) begin
			register_file[register_write_address] <= register_write_data;
		end

	end 
    
end

endmodule

modules/instruction_decoder.v
// **************************************************
// Core Control Unit
// **************************************************

module instruction_decoder(
	input wire [31:0] instruction_register,
	output wire register_write_enable,
	output wire alu_immediate_enable,
	output wire [2:0] immediate_select,
	output wire [4:0] register_write_address,
	output wire [4:0] register_read_address_a,
	output wire [4:0] register_read_address_b,
	output wire data_memory_write_enable,
	output wire data_memory_write_back_enable,
	output reg [3:0] alu_operation
);

// ------------- Wire Declaration ------------

wire [2:0] funct3 = instruction_register[14:12];
wire [6:0] funct7 = instruction_register[31:25];

// ---------- Parse Instruction Data ---------

wire alu_register_operation           = (instruction_register[6:2] == 5'b01100); // rd <- rs1 OP rs2
wire alu_immediate_operation          = (instruction_register[6:2] == 5'b00100); // rd <- rs1 OP Iimm
wire branch_operation                 = (instruction_register[6:2] == 5'b11000); // (rs1 OP rs2) ? PC <- PC + Bimm : nothing
wire jump_and_link_pc_operation       = (instruction_register[6:2] == 5'b01111); // rd <- PC + 4; PC <- PC + Jimm
wire jump_and_link_register_operation = (instruction_register[6:2] == 5'b11001); // rd <- PC + 4; PC <- rs1 + Iimm
wire add_upper_immediate_pc_operation = (instruction_register[6:2] == 5'b00101); // rd <- PC + Uimm 
wire load_upper_immediate_operation   = (instruction_register[6:2] == 5'b01101); // rd <- Uimm
wire load_operation                   = (instruction_register[6:2] == 5'b00000); // rd <- memory[rs1 + Iimm]
wire store_operation                  = (instruction_register[6:2] == 5'b01000); // memory[rs1 + Simm] <- rs2
wire system_operation                 = (instruction_register[6:2] == 5'b11100); // reserved

// ---------- Memory Access Control ----------

assign data_memory_write_enable = store_operation ? 1'b1 : 1'b0;

assign data_memory_write_back_enable = load_operation ? 1'b1 : 1'b0;

// ---------- ALU Operation Control ----------

always @(*) begin
	case(funct3) 
		3'b000: alu_operation = (funct7[5] & instruction_register[5]) ? (4'b0001) : // sub
		(4'b0000); // add
		3'b001: alu_operation = 4'b0010; // register-shift left
		3'b010: alu_operation = 4'b0011; // set less than
		3'b011: alu_operation = 4'b0100; // set less than unsigned
		3'b100: alu_operation = 4'b0101; // xor
		3'b101: alu_operation = funct7[5] ? (4'b0110) : // register-shift right arithmetic
		(4'b0111); // register-shift right logical
		3'b110: alu_operation = (4'b1000); // or
		3'b111: alu_operation = (4'b1001); // and
	endcase
end

// ------ ALU Immediate Select Control ------

assign alu_immediate_enable = alu_immediate_operation ? 1'b1 : 1'b0;

// --------- Register Write Control ---------

assign register_write_address = instruction_register[11:7];
assign register_read_address_a = instruction_register[19:15];
assign register_read_address_b = instruction_register[24:20];

assign register_write_enable = alu_register_operation ? 1'b1 : 
	alu_immediate_operation ? 1'b1 :
	jump_and_link_pc_operation ? 1'b1 :
	add_upper_immediate_pc_operation ? 1'b1 :
	load_operation ? 1'b1 :
	1'b0;

// ------- Immediate Generator Control -------

assign immediate_select = alu_register_operation ? 3'b111 : // Unused 
	alu_immediate_operation ? 3'b001 : // Iimm
	branch_operation ? 3'b011 : // Bimm
	jump_and_link_register_operation ? 3'b001 : // Iimm
	add_upper_immediate_pc_operation ? 3'b000 : // Uimm
	load_upper_immediate_operation ? 3'b000 : // Uimm
	load_operation ? 3'b001 : // Iimm
	store_operation ? 3'b010 : // Simm
	system_operation ? 3'b111 : // Unused
	3'b111; // Base Case

endmodule

modules/instruction_register.v
module instruction_register (
    input wire clk,
    input wire rst,
    input wire [31:0] instruction_memory_read_data,
    output reg [31:0] instruction_register
);

always @(posedge clk) begin

    if (~rst) begin
        instruction_register <= 32'b0;
    end 
    else begin
        instruction_register <= instruction_memory_read_data;
    end
    
end

endmodule

modules/data_memory.v
// **************************************************
// Data Memory (12 bit block)
// **************************************************

module data_memory (
	input clk,
	input rst,
	input data_memory_write_enable,
	input [31:0] data_memory_access_address,
	input [31:0] data_memory_write_data,
	output wire [31:0] data_memory_read_data
);

// -------------- Memory Block --------------

parameter memory_size = 4095;
reg [31:0] memory[0:memory_size];

// ---------------- IO Control ----------------

assign data_memory_read_data = data_memory_write_enable ? data_memory_write_data : memory[data_memory_access_address];

always @(posedge clk) begin

    if (~rst) begin
    	for (integer i = 0; i < memory_size; i = i + 1) begin
		memory[i] <= 32'b0;
	end
    end else if (data_memory_write_enable) begin
        memory[data_memory_access_address] <= data_memory_write_data;
    end
    
end

endmodule

modules/instruction_memory.v
// **************************************************
// Instruction Memory (12 bit block)
// **************************************************

module instruction_memory (
	input clk,
	input instruction_memory_write_enable,
	input [31:0] instruction_memory_access_address,
	input [31:0] instruction_memory_write_data,
	output wire [31:0] instruction_memory_read_data
);

// -------------- Memory Block --------------

parameter memory_size = 4095;
reg [31:0] memory[0:memory_size];

initial $readmemh("mem.hex", memory);

// ---------------- IO Control ----------------

assign instruction_memory_read_data = instruction_memory_write_enable ? instruction_memory_write_data : memory[instruction_memory_access_address];

always @(posedge clk) begin

    if (instruction_memory_write_enable) begin
        memory[instruction_memory_access_address] <= instruction_memory_write_data;
    end

end

endmodule

modules/program_counter.v
// **************************************************
// Program Counter
// **************************************************

module program_counter(
	input wire clk,
	input wire rst,
	output reg[31:0] program_counter
);

always @(posedge clk) begin

	if (~rst) begin
			program_counter <= 32'b0;
	end
	else begin 
		program_counter <= program_counter + 1;
	end
	
end

endmodule

modules/waverv.v
// **************************************************
// Root/Instantiator Module
// **************************************************

module waverv (
	input clk,
	input rst
);

// ------ Wire Declaration By Originator -----

// Program Counter
wire [31:0] program_counter;

// Memory
wire [31:0] instruction_memory_read_data;
wire [31:0] data_memory_read_data;

// Instruction Register
wire [31:0] instruction_register;

// Instruction Decoder
wire register_write_enable;
wire alu_immediate_enable;
wire [2:0] immediate_select;
wire [4:0] register_write_address;
wire [4:0] register_read_address_a;
wire [4:0] register_read_address_b;
wire data_memory_write_enable;
wire data_memory_write_back_enable;
wire [3:0] alu_operation;

// Register File
wire [31:0] register_read_data_a;
wire [31:0] register_read_data_b;

// Immediate Generator
wire [4:0] alu_shamt;
wire [31:0] immediate_data;

// ALU
wire [31:0] alu_out;

// ----------- Module Instantiation ----------

program_counter program_counter_inst(
	.clk(clk),
	.rst(rst),
	.program_counter(program_counter)
);

instruction_memory instruction_memory_inst (
	.clk(clk),
	.instruction_memory_write_enable(1'b0),
	.instruction_memory_access_address(program_counter),
	.instruction_memory_write_data(32'b0),
	.instruction_memory_read_data(instruction_memory_read_data)
);

data_memory data_memory_inst (
	.clk(clk),
	.rst(rst),
	.data_memory_write_enable(data_memory_write_enable),
	.data_memory_access_address(alu_out),
	.data_memory_write_data(register_read_data_b),
	.data_memory_read_data(data_memory_read_data)
);

instruction_register instruction_register_inst (
	.clk(clk),
	.rst(rst),
	.instruction_memory_read_data(instruction_memory_read_data),
	.instruction_register(instruction_register)
);

instruction_decoder instruction_decoder_inst (
	.instruction_register(instruction_register),
	.register_write_enable(register_write_enable),
	.alu_immediate_enable(alu_immediate_enable),
	.immediate_select(immediate_select),
	.register_write_address(register_write_address),
	.register_read_address_a(register_read_address_a),
	.register_read_address_b(register_read_address_b),
	.data_memory_write_enable(data_memory_write_enable),
	.data_memory_write_back_enable(data_memory_write_back_enable),
	.alu_operation(alu_operation)
);

register_file register_file_inst (
	.clk(clk),
	.rst(rst),
	.register_write_enable(register_write_enable),
	.register_write_address(register_write_address),
	.register_read_address_a(register_read_address_a),
	.register_read_address_b(register_read_address_b),
	.data_memory_write_back_enable(data_memory_write_back_enable),
	.alu_out(alu_out),
	.data_memory_read_data(data_memory_read_data),
	.register_read_data_a(register_read_data_a),
	.register_read_data_b(register_read_data_b)
);

immediate_generator immediate_generator_inst (
	.instruction_register(instruction_register),
	.immediate_select(immediate_select),
	.alu_shamt(alu_shamt),
	.immediate_data(immediate_data)
);

alu alu_inst (
	.rst(rst),
	.alu_immediate_enable(alu_immediate_enable),
	.register_read_data_a(register_read_data_a),
	.register_read_data_b(register_read_data_b),
	.immediate_data(immediate_data),
	.alu_operation(alu_operation),
	.alu_shamt(alu_shamt),
	.alu_out(alu_out)
);

endmodule

modules/test_bench.v
`timescale 1ps/1ps

module test_bench;

reg clk;
reg rst;

waverv waverv_inst (
    .clk(clk),
    .rst(rst)
);

initial begin 

    $dumpfile("counter.vcd");
    $dumpvars(0, test_bench);

    rst = 0;
    #5;
    rst = 1;

    #1000;
    $finish;

end

initial clk = 0;
always #1 clk = ~clk;

endmodule

test_data/counter.vcd
$date
	Fri Jan  9 14:41:34 2026
$end
$version
	Icarus Verilog
$end
$timescale
	1ps
$end
$scope module test_bench $end
$var reg 1 ! clk $end
$var reg 1 " rst $end
$scope module waverv_inst $end
$var wire 1 ! clk $end
$var wire 1 " rst $end
$var wire 1 # register_write_enable $end
$var wire 5 $ register_write_address [4:0] $end
$var wire 32 % register_read_data_b [31:0] $end
$var wire 32 & register_read_data_a [31:0] $end
$var wire 5 ' register_read_address_b [4:0] $end
$var wire 5 ( register_read_address_a [4:0] $end
$var wire 32 ) program_counter [31:0] $end
$var wire 32 * instruction_register [31:0] $end
$var wire 32 + instruction_memory_read_data [31:0] $end
$var wire 3 , immediate_select [2:0] $end
$var wire 32 - immediate_data [31:0] $end
$var wire 1 . data_memory_write_enable $end
$var wire 1 / data_memory_write_back_enable $end
$var wire 32 0 data_memory_read_data [31:0] $end
$var wire 5 1 alu_shamt [4:0] $end
$var wire 32 2 alu_out [31:0] $end
$var wire 4 3 alu_operation [3:0] $end
$var wire 1 4 alu_immediate_enable $end
$scope module alu_inst $end
$var wire 32 5 alu_input_1 [31:0] $end
$var wire 1 " rst $end
$var wire 32 6 register_read_data_b [31:0] $end
$var wire 32 7 register_read_data_a [31:0] $end
$var wire 32 8 immediate_data [31:0] $end
$var wire 5 9 alu_shamt [4:0] $end
$var wire 4 : alu_operation [3:0] $end
$var wire 32 ; alu_input_2 [31:0] $end
$var wire 1 4 alu_immediate_enable $end
$var reg 32 < alu_out [31:0] $end
$upscope $end
$scope module data_memory_inst $end
$var wire 1 ! clk $end
$var wire 32 = data_memory_access_address [31:0] $end
$var wire 1 " rst $end
$var wire 1 . data_memory_write_enable $end
$var wire 32 > data_memory_write_data [31:0] $end
$var wire 32 ? data_memory_read_data [31:0] $end
$var parameter 32 @ memory_size $end
$scope begin $ivl_for_loop0 $end
$var integer 32 A i [31:0] $end
$upscope $end
$upscope $end
$scope module immediate_generator_inst $end
$var wire 32 B instruction_register [31:0] $end
$var wire 3 C immediate_select [2:0] $end
$var wire 5 D alu_shamt [4:0] $end
$var wire 1 E Uimm $end
$var wire 1 F Simm $end
$var wire 1 G Jimm $end
$var wire 1 H Iimm $end
$var wire 1 I Bimm $end
$var reg 32 J immediate_data [31:0] $end
$upscope $end
$scope module instruction_decoder_inst $end
$var wire 1 K system_operation $end
$var wire 1 L store_operation $end
$var wire 1 # register_write_enable $end
$var wire 5 M register_write_address [4:0] $end
$var wire 5 N register_read_address_b [4:0] $end
$var wire 5 O register_read_address_a [4:0] $end
$var wire 1 P load_upper_immediate_operation $end
$var wire 1 Q load_operation $end
$var wire 1 R jump_and_link_register_operation $end
$var wire 1 S jump_and_link_pc_operation $end
$var wire 32 T instruction_register [31:0] $end
$var wire 3 U immediate_select [2:0] $end
$var wire 7 V funct7 [6:0] $end
$var wire 3 W funct3 [2:0] $end
$var wire 1 . data_memory_write_enable $end
$var wire 1 / data_memory_write_back_enable $end
$var wire 1 X branch_operation $end
$var wire 1 Y alu_register_operation $end
$var wire 1 Z alu_immediate_operation $end
$var wire 1 4 alu_immediate_enable $end
$var wire 1 [ add_upper_immediate_pc_operation $end
$var reg 4 \ alu_operation [3:0] $end
$upscope $end
$scope module instruction_memory_inst $end
$var wire 1 ! clk $end
$var wire 32 ] instruction_memory_read_data [31:0] $end
$var wire 32 ^ instruction_memory_write_data [31:0] $end
$var wire 1 _ instruction_memory_write_enable $end
$var wire 32 ` instruction_memory_access_address [31:0] $end
$var parameter 32 a memory_size $end
$upscope $end
$scope module instruction_register_inst $end
$var wire 1 ! clk $end
$var wire 32 b instruction_memory_read_data [31:0] $end
$var wire 1 " rst $end
$var reg 32 c instruction_register [31:0] $end
$upscope $end
$scope module program_counter_inst $end
$var wire 1 ! clk $end
$var wire 1 " rst $end
$var reg 32 d program_counter [31:0] $end
$upscope $end
$scope module register_file_inst $end
$var wire 32 e alu_out [31:0] $end
$var wire 1 ! clk $end
$var wire 32 f data_memory_read_data [31:0] $end
$var wire 1 / data_memory_write_back_enable $end
$var wire 5 g register_read_address_a [4:0] $end
$var wire 5 h register_read_address_b [4:0] $end
$var wire 32 i register_read_data_a [31:0] $end
$var wire 32 j register_read_data_b [31:0] $end
$var wire 5 k register_write_address [4:0] $end
$var wire 1 # register_write_enable $end
$var wire 1 " rst $end
$var wire 32 l register_write_data [31:0] $end
$scope begin $ivl_for_loop1 $end
$var integer 32 m i [31:0] $end
$upscope $end
$upscope $end
$upscope $end
$upscope $end
$enddefinitions $end
$comment Show the parameter values. $end
$dumpall
b111111111111 a
b111111111111 @
$end
#0
$dumpvars
bx m
bx l
bx k
bx j
bx i
bx h
bx g
bx f
b0 e
bx d
bx c
bx b
bx `
0_
b0 ^
bx ]
bx \
x[
xZ
xY
xX
bx W
bx V
bx U
bx T
xS
xR
xQ
xP
bx O
bx N
bx M
xL
xK
b0 J
0I
xH
0G
xF
0E
b0 D
bx C
bx B
bx A
bx ?
bx >
b0 =
b0 <
bx ;
bx :
b0 9
b0 8
bx 7
bx 6
bx 5
x4
bx 3
b0 2
b0 1
bx 0
x/
x.
b0 -
bx ,
bx +
bx *
bx )
bx (
bx '
bx &
bx %
bx $
x#
0"
0!
$end
#1
b1 ,
b1 C
b1 U
1#
b0 l
b0 ;
0.
1/
04
b0 3
b0 :
b0 \
0F
0H
b0 0
b0 ?
b0 f
b0 %
b0 6
b0 >
b0 j
b0 '
b0 N
b0 h
b0 5
b0 &
b0 7
b0 i
b0 (
b0 O
b0 g
b0 $
b0 M
b0 k
0K
0L
1Q
0P
0[
0R
0S
0X
0Z
0Y
b0 V
b0 W
b0 +
b0 ]
b0 b
b0 )
b0 `
b0 d
b0 *
b0 B
b0 T
b0 c
b100000 m
b111111111111 A
1!
#2
0!
#3
b100000 m
b111111111111 A
1!
#4
0!
#5
b1 )
b1 `
b1 d
1!
1"
#6
0!
#7
b10 )
b10 `
b10 d
1!
#8
0!
#9
b100001000000010010011 +
b100001000000010010011 ]
b100001000000010010011 b
b11 )
b11 `
b11 d
1!
#10
0!
#11
b1 l
b1 2
b1 <
b1 =
b1 e
b1 1
b1 9
b1 D
b1 ;
b1 -
b1 8
b1 J
0/
14
1F
1H
b1 '
b1 N
b1 h
b1 (
b1 O
b1 g
b1 $
b1 M
b1 k
0Q
1Z
b100001000000010010011 *
b100001000000010010011 B
b100001000000010010011 T
b100001000000010010011 c
b100001000000010110011 +
b100001000000010110011 ]
b100001000000010110011 b
b100 )
b100 `
b100 d
1!
#12
0!
#13
b10 l
b10 2
b10 <
b10 =
b10 e
b0 1
b0 9
b0 D
b0 -
b0 8
b0 J
04
b111 ,
b111 C
b111 U
0Z
1Y
b101 )
b101 `
b101 d
b100001000000010110011 *
b100001000000010110011 B
b100001000000010110011 T
b100001000000010110011 c
b1 5
b1 &
b1 7
b1 i
b1 %
b1 6
b1 >
b1 j
1!
#14
0!
#15
b100 l
b100 2
b100 <
b100 =
b100 e
b10 ;
b10 5
b10 &
b10 7
b10 i
b10 %
b10 6
b10 >
b10 j
b110 )
b110 `
b110 d
1!
#16
0!
#17
b1000 l
b1000 2
b1000 <
b1000 =
b1000 e
b100 ;
b111 )
b111 `
b111 d
b100 5
b100 &
b100 7
b100 i
b100 %
b100 6
b100 >
b100 j
1!
#18
0!
#19
b10000 l
b10000 2
b10000 <
b10000 =
b10000 e
b1000 ;
b1000 5
b1000 &
b1000 7
b1000 i
b1000 %
b1000 6
b1000 >
b1000 j
b1000 )
b1000 `
b1000 d
1!
#20
0!
#21
b100000 l
b100000 2
b100000 <
b100000 =
b100000 e
b10000 ;
b1001 )
b1001 `
b1001 d
b10000 5
b10000 &
b10000 7
b10000 i
b10000 %
b10000 6
b10000 >
b10000 j
1!
#22
0!
#23
b1000000 l
b1000000 2
b1000000 <
b1000000 =
b1000000 e
b100000 ;
b100000 5
b100000 &
b100000 7
b100000 i
b100000 %
b100000 6
b100000 >
b100000 j
b1010 )
b1010 `
b1010 d
1!
#24
0!
#25
b10000000 l
b10000000 2
b10000000 <
b10000000 =
b10000000 e
b1000000 ;
b1011 )
b1011 `
b1011 d
b1000000 5
b1000000 &
b1000000 7
b1000000 i
b1000000 %
b1000000 6
b1000000 >
b1000000 j
1!
#26
0!
#27
b100000000 l
b100000000 2
b100000000 <
b100000000 =
b100000000 e
b10000000 ;
b10000000 5
b10000000 &
b10000000 7
b10000000 i
b10000000 %
b10000000 6
b10000000 >
b10000000 j
b1100 )
b1100 `
b1100 d
1!
#28
0!
#29
b1000000000 l
b1000000000 2
b1000000000 <
b1000000000 =
b1000000000 e
b100000000 ;
b1101 )
b1101 `
b1101 d
b100000000 5
b100000000 &
b100000000 7
b100000000 i
b100000000 %
b100000000 6
b100000000 >
b100000000 j
1!
#30
0!
#31
b10000000000 l
b10000000000 2
b10000000000 <
b10000000000 =
b10000000000 e
b1000000000 ;
b1000000000 5
b1000000000 &
b1000000000 7
b1000000000 i
b1000000000 %
b1000000000 6
b1000000000 >
b1000000000 j
b1110 )
b1110 `
b1110 d
1!
#32
0!
#33
b100000000000 l
b100000000000 2
b100000000000 <
b100000000000 =
b100000000000 e
b10000000000 ;
b1111 )
b1111 `
b1111 d
b10000000000 5
b10000000000 &
b10000000000 7
b10000000000 i
b10000000000 %
b10000000000 6
b10000000000 >
b10000000000 j
1!
#34
0!
#35
bx 0
bx ?
bx f
b1000000000000 l
b1000000000000 2
b1000000000000 <
b1000000000000 =
b1000000000000 e
b100000000000 ;
b100000000000 5
b100000000000 &
b100000000000 7
b100000000000 i
b100000000000 %
b100000000000 6
b100000000000 >
b100000000000 j
b10000 )
b10000 `
b10000 d
1!
#36
0!
#37
b10000000000000 l
b10000000000000 2
b10000000000000 <
b10000000000000 =
b10000000000000 e
b1000000000000 ;
b10001 )
b10001 `
b10001 d
b1000000000000 5
b1000000000000 &
b1000000000000 7
b1000000000000 i
b1000000000000 %
b1000000000000 6
b1000000000000 >
b1000000000000 j
1!
#38
0!
#39
b100000000000000 l
b100000000000000 2
b100000000000000 <
b100000000000000 =
b100000000000000 e
b10000000000000 ;
b10000000000000 5
b10000000000000 &
b10000000000000 7
b10000000000000 i
b10000000000000 %
b10000000000000 6
b10000000000000 >
b10000000000000 j
b10010 )
b10010 `
b10010 d
1!
#40
0!
#41
b1000000000000000 l
b1000000000000000 2
b1000000000000000 <
b1000000000000000 =
b1000000000000000 e
b100000000000000 ;
b10011 )
b10011 `
b10011 d
b100000000000000 5
b100000000000000 &
b100000000000000 7
b100000000000000 i
b100000000000000 %
b100000000000000 6
b100000000000000 >
b100000000000000 j
1!
#42
0!
#43
b10000000000000000 l
b10000000000000000 2
b10000000000000000 <
b10000000000000000 =
b10000000000000000 e
b1000000000000000 ;
b1000000000000000 5
b1000000000000000 &
b1000000000000000 7
b1000000000000000 i
b1000000000000000 %
b1000000000000000 6
b1000000000000000 >
b1000000000000000 j
b10100 )
b10100 `
b10100 d
1!
#44
0!
#45
b100000000000000000 l
b100000000000000000 2
b100000000000000000 <
b100000000000000000 =
b100000000000000000 e
b10000000000000000 ;
b10101 )
b10101 `
b10101 d
b10000000000000000 5
b10000000000000000 &
b10000000000000000 7
b10000000000000000 i
b10000000000000000 %
b10000000000000000 6
b10000000000000000 >
b10000000000000000 j
1!
#46
0!
#47
b1000000000000000000 l
b1000000000000000000 2
b1000000000000000000 <
b1000000000000000000 =
b1000000000000000000 e
b100000000000000000 ;
b100000000000000000 5
b100000000000000000 &
b100000000000000000 7
b100000000000000000 i
b100000000000000000 %
b100000000000000000 6
b100000000000000000 >
b100000000000000000 j
b10110 )
b10110 `
b10110 d
1!
#48
0!
#49
b10000000000000000000 l
b10000000000000000000 2
b10000000000000000000 <
b10000000000000000000 =
b10000000000000000000 e
b1000000000000000000 ;
b10111 )
b10111 `
b10111 d
b1000000000000000000 5
b1000000000000000000 &
b1000000000000000000 7
b1000000000000000000 i
b1000000000000000000 %
b1000000000000000000 6
b1000000000000000000 >
b1000000000000000000 j
1!
#50
0!
#51
b100000000000000000000 l
b100000000000000000000 2
b100000000000000000000 <
b100000000000000000000 =
b100000000000000000000 e
b10000000000000000000 ;
b10000000000000000000 5
b10000000000000000000 &
b10000000000000000000 7
b10000000000000000000 i
b10000000000000000000 %
b10000000000000000000 6
b10000000000000000000 >
b10000000000000000000 j
b11000 )
b11000 `
b11000 d
1!
#52
0!
#53
b1000000000000000000000 l
b1000000000000000000000 2
b1000000000000000000000 <
b1000000000000000000000 =
b1000000000000000000000 e
b100000000000000000000 ;
b11001 )
b11001 `
b11001 d
b100000000000000000000 5
b100000000000000000000 &
b100000000000000000000 7
b100000000000000000000 i
b100000000000000000000 %
b100000000000000000000 6
b100000000000000000000 >
b100000000000000000000 j
1!
#54
0!
#55
b10000000000000000000000 l
b10000000000000000000000 2
b10000000000000000000000 <
b10000000000000000000000 =
b10000000000000000000000 e
b1000000000000000000000 ;
b1000000000000000000000 5
b1000000000000000000000 &
b1000000000000000000000 7
b1000000000000000000000 i
b1000000000000000000000 %
b1000000000000000000000 6
b1000000000000000000000 >
b1000000000000000000000 j
b11010 )
b11010 `
b11010 d
1!
#56
0!
#57
b100000000000000000000000 l
b100000000000000000000000 2
b100000000000000000000000 <
b100000000000000000000000 =
b100000000000000000000000 e
b10000000000000000000000 ;
b11011 )
b11011 `
b11011 d
b10000000000000000000000 5
b10000000000000000000000 &
b10000000000000000000000 7
b10000000000000000000000 i
b10000000000000000000000 %
b10000000000000000000000 6
b10000000000000000000000 >
b10000000000000000000000 j
1!
#58
0!
#59
b1000000000000000000000000 l
b1000000000000000000000000 2
b1000000000000000000000000 <
b1000000000000000000000000 =
b1000000000000000000000000 e
b100000000000000000000000 ;
b100000000000000000000000 5
b100000000000000000000000 &
b100000000000000000000000 7
b100000000000000000000000 i
b100000000000000000000000 %
b100000000000000000000000 6
b100000000000000000000000 >
b100000000000000000000000 j
b11100 )
b11100 `
b11100 d
1!
#60
0!
#61
b10000000000000000000000000 l
b10000000000000000000000000 2
b10000000000000000000000000 <
b10000000000000000000000000 =
b10000000000000000000000000 e
b1000000000000000000000000 ;
b11101 )
b11101 `
b11101 d
b1000000000000000000000000 5
b1000000000000000000000000 &
b1000000000000000000000000 7
b1000000000000000000000000 i
b1000000000000000000000000 %
b1000000000000000000000000 6
b1000000000000000000000000 >
b1000000000000000000000000 j
1!
#62
0!
#63
b100000000000000000000000000 l
b100000000000000000000000000 2
b100000000000000000000000000 <
b100000000000000000000000000 =
b100000000000000000000000000 e
b10000000000000000000000000 ;
b10000000000000000000000000 5
b10000000000000000000000000 &
b10000000000000000000000000 7
b10000000000000000000000000 i
b10000000000000000000000000 %
b10000000000000000000000000 6
b10000000000000000000000000 >
b10000000000000000000000000 j
b11110 )
b11110 `
b11110 d
1!
#64
0!
#65
b1000000000000000000000000000 l
b1000000000000000000000000000 2
b1000000000000000000000000000 <
b1000000000000000000000000000 =
b1000000000000000000000000000 e
b100000000000000000000000000 ;
b11111 )
b11111 `
b11111 d
b100000000000000000000000000 5
b100000000000000000000000000 &
b100000000000000000000000000 7
b100000000000000000000000000 i
b100000000000000000000000000 %
b100000000000000000000000000 6
b100000000000000000000000000 >
b100000000000000000000000000 j
1!
#66
0!
#67
b10000000000000000000000000000 l
b10000000000000000000000000000 2
b10000000000000000000000000000 <
b10000000000000000000000000000 =
b10000000000000000000000000000 e
b1000000000000000000000000000 ;
b1000000000000000000000000000 5
b1000000000000000000000000000 &
b1000000000000000000000000000 7
b1000000000000000000000000000 i
b1000000000000000000000000000 %
b1000000000000000000000000000 6
b1000000000000000000000000000 >
b1000000000000000000000000000 j
b100000 )
b100000 `
b100000 d
1!
#68
0!
#69
b100000000000000000000000000000 l
b100000000000000000000000000000 2
b100000000000000000000000000000 <
b100000000000000000000000000000 =
b100000000000000000000000000000 e
b10000000000000000000000000000 ;
b100001 )
b100001 `
b100001 d
b10000000000000000000000000000 5
b10000000000000000000000000000 &
b10000000000000000000000000000 7
b10000000000000000000000000000 i
b10000000000000000000000000000 %
b10000000000000000000000000000 6
b10000000000000000000000000000 >
b10000000000000000000000000000 j
1!
#70
0!
#71
b1000000000000000000000000000000 l
b1000000000000000000000000000000 2
b1000000000000000000000000000000 <
b1000000000000000000000000000000 =
b1000000000000000000000000000000 e
b100000000000000000000000000000 ;
b100000000000000000000000000000 5
b100000000000000000000000000000 &
b100000000000000000000000000000 7
b100000000000000000000000000000 i
b100000000000000000000000000000 %
b100000000000000000000000000000 6
b100000000000000000000000000000 >
b100000000000000000000000000000 j
b100010 )
b100010 `
b100010 d
1!
#72
0!
#73
b10000000000000000000000000000000 l
b10000000000000000000000000000000 2
b10000000000000000000000000000000 <
b10000000000000000000000000000000 =
b10000000000000000000000000000000 e
b1000000000000000000000000000000 ;
b100011 )
b100011 `
b100011 d
b1000000000000000000000000000000 5
b1000000000000000000000000000000 &
b1000000000000000000000000000000 7
b1000000000000000000000000000000 i
b1000000000000000000000000000000 %
b1000000000000000000000000000000 6
b1000000000000000000000000000000 >
b1000000000000000000000000000000 j
1!
#74
0!
#75
b0 0
b0 ?
b0 f
b0 l
b0 2
b0 <
b0 =
b0 e
b10000000000000000000000000000000 ;
b10000000000000000000000000000000 5
b10000000000000000000000000000000 &
b10000000000000000000000000000000 7
b10000000000000000000000000000000 i
b10000000000000000000000000000000 %
b10000000000000000000000000000000 6
b10000000000000000000000000000000 >
b10000000000000000000000000000000 j
b100100 )
b100100 `
b100100 d
1!
#76
0!
#77
b0 ;
b100101 )
b100101 `
b100101 d
b0 5
b0 &
b0 7
b0 i
b0 %
b0 6
b0 >
b0 j
1!
#78
0!
#79
b100110 )
b100110 `
b100110 d
1!
#80
0!
#81
b100111 )
b100111 `
b100111 d
1!
#82
0!
#83
b101000 )
b101000 `
b101000 d
1!
#84
0!
#85
b101001 )
b101001 `
b101001 d
1!
#86
0!
#87
b101010 )
b101010 `
b101010 d
1!
